basic_model/__init__.py
basic_model-0.4.2.dist-info/LICENSE
basic_model-0.4.2.dist-info/METADATA
basic_model-0.4.2.dist-info/WHEEL
basic_model-0.4.2.dist-info/top_level.txt
basic_model-0.4.2.dist-info/RECORD
