Metadata-Version: 2.1
Name: basic-model
Version: 0.4.2
Summary: Serialization and deserialization made simple
Home-page: https://github.com/smart-code-eu/basic_model
Author: (C) 2020 SMART CODE, razvoj aplikacij, d.o.o.
Author-email: info@smartcode.eu
License: UNKNOWN
Platform: UNKNOWN
Classifier: Programming Language :: Python :: 3
Requires-Dist: six (==1.12.0)
Requires-Dist: typing (==3.6.4)
Requires-Dist: python-dateutil (==2.8.0)
